{
    "Info": [
        {
            "Name": "time",
            "Up": false
        },
        {
            "Name": "rank",
            "Up": false
        },
        {
            "Name": "up_time",
            "Up": false
        }
    ],
    "Value": [
        [
            107.69999999999999,
            5.0,
            30.4
        ],
        [
            107.69999999999999,
            6.0,
            30.4
        ],
        [
            107.1,
            3.0,
            30.4
        ],
        [
            106.998,
            1.0,
            30.4
        ],
        [
            111.10199999999999,
            13.0,
            30.4
        ],
        [
            108.198,
            8.0,
            30.4
        ],
        [
            108.3,
            9.0,
            30.4
        ],
        [
            108.402,
            10.0,
            30.4
        ],
        [
            107.50200000000001,
            4.0,
            30.4
        ],
        [
            107.1,
            2.0,
            30.4
        ],
        [
            108.102,
            7.0,
            30.4
        ],
        [
            61.001999999999995,
            10.0,
            35.9
        ],
        [
            60.89999999999999,
            9.0,
            35.9
        ],
        [
            60.6,
            6.0,
            35.9
        ],
        [
            62.502,
            11.0,
            35.9
        ],
        [
            59.4,
            2.0,
            35.9
        ],
        [
            59.1,
            1.0,
            35.9
        ],
        [
            60.89999999999999,
            8.0,
            35.9
        ],
        [
            59.7,
            3.0,
            35.9
        ],
        [
            60.702000000000005,
            7.0,
            35.9
        ],
        [
            108.702,
            4.0,
            30.5
        ],
        [
            110.1,
            10.0,
            30.5
        ],
        [
            109.99799999999999,
            9.0,
            30.5
        ],
        [
            107.80199999999999,
            1.0,
            30.5
        ],
        [
            109.098,
            6.0,
            30.5
        ],
        [
            108.702,
            5.0,
            30.5
        ],
        [
            108.60000000000001,
            3.0,
            30.5
        ],
        [
            111.702,
            12.0,
            30.5
        ],
        [
            110.898,
            11.0,
            30.5
        ],
        [
            109.398,
            8.0,
            30.5
        ],
        [
            109.302,
            7.0,
            30.5
        ],
        [
            107.898,
            2.0,
            30.5
        ]
    ]
}